CMakeLists.txt
LICENSE
MANIFEST.in
README.md
metrics_central_1.png
onedviewer.png
pyproject.toml
setup.py
examples/display_multiple_channels_cpp.cpp
examples/display_oneD_data_cpp.cpp
examples/show_blank_cpp.cpp
examples/pyvenv/lib/python3.10/site-packages/numpy/core/tests/data/generate_umath_validation_data.cpp
examples/pyvenv/lib64/python3.10/site-packages/numpy/core/tests/data/generate_umath_validation_data.cpp
include/roboflex_imgui/implot_node.h
include/roboflex_imgui/metrics_television.h
include/roboflex_imgui/oned_television.h
python/CMakeLists.txt
python/__init__.py
python/generate_test_metrics.py
python/metrics_central.py
python/pybindings.cpp
python/pyvenv/lib/python3.10/site-packages/numpy/core/tests/data/generate_umath_validation_data.cpp
python/pyvenv/lib64/python3.10/site-packages/numpy/core/tests/data/generate_umath_validation_data.cpp
roboflex.imgui.egg-info/PKG-INFO
roboflex.imgui.egg-info/SOURCES.txt
roboflex.imgui.egg-info/dependency_links.txt
roboflex.imgui.egg-info/requires.txt
roboflex.imgui.egg-info/top_level.txt
src/implot_node.cpp
src/metrics_television.cpp
src/oned_television.cpp