Metadata-Version: 2.1
Name: roboflex.imgui
Version: 0.1.16
Summary: Roboflex Visualization/GUI Library using IMGUI/IMPLOT
Home-page: https://github.com/flexrobotics/roboflex_imgui
Author: Colin Prepscius
Author-email: colinprepscius@gmail.com
License: MIT
Keywords: imgui,implot,gui,visualization,robotics,middleware,flexbuffers,python,c++,c++20
Platform: UNKNOWN
Classifier: Intended Audience :: Developers
Classifier: License :: OSI Approved :: MIT License
Classifier: Topic :: Software Development :: Libraries :: Python Modules
Classifier: Topic :: Software Development :: Embedded Systems
Classifier: Framework :: Robot Framework
Classifier: Framework :: Robot Framework :: Library
Classifier: Framework :: Robot Framework :: Tool
Classifier: Programming Language :: C++
Classifier: Programming Language :: Python :: 3
Requires-Python: >=3.6
License-File: LICENSE
